klein_queue/__init__.py
klein_queue/errors.py
klein_queue/rabbitmq/__init__.py
klein_queue/rabbitmq/api.py
klein_queue/rabbitmq/connect.py
klein_queue/rabbitmq/consumer.py
klein_queue/rabbitmq/exceptions.py
klein_queue/rabbitmq/publisher.py
klein_queue-2.4.6.dist-info/LICENSE.txt
klein_queue-2.4.6.dist-info/METADATA
klein_queue-2.4.6.dist-info/WHEEL
klein_queue-2.4.6.dist-info/top_level.txt
klein_queue-2.4.6.dist-info/zip-safe
klein_queue-2.4.6.dist-info/RECORD
