Metadata-Version: 2.1
Name: klein_queue
Version: 2.4.6
Summary: RabbitMQ integration
Home-page: http://github.com/mdcatapult/py-queue
Author: Medicines Discovery Catapult
Author-email: SoftwareEngineering@md.catapult.org.uk
License: Apache V2
License-File: LICENSE.txt
Requires-Dist: klein-config >=3.0.0
Requires-Dist: pika <2.0.0,>=1.1.0
Requires-Dist: requests <3.0.0,>=2.23.0
